anonymize/__init__.py
anonymize/anonymize.py
anonymize_UU-0.1.7.dist-info/METADATA
anonymize_UU-0.1.7.dist-info/WHEEL
anonymize_UU-0.1.7.dist-info/top_level.txt
anonymize_UU-0.1.7.dist-info/RECORD
