Metadata-Version: 2.1
Name: anonymize-UU
Version: 0.1.7
Summary: A tool to substitue patterns/names in a file tree
Home-page: https://github.com/cskaandorp/anonymize
Author: C.S. Kaandorp
Author-email: c.s.kaandorp@uu.nl
License: MIT
Platform: UNKNOWN
Requires-Python: >=3.6
